<Ui xmlns="http://www.blizzard.com/wow/ui/" xmlns:xsi="http://www.w3.org/2001/XMLSchema-instance" xsi:schemaLocation="http://www.blizzard.com/wow/ui/
..\FrameXML\UI.xsd">

  <!-- /*******************/ CUSTOM TEMPLATES /*************************/ -->

  <!-- nice icon button template -->
  <Button name="NysTDL_IconButtonTemplate" virtual="true">
    <NormalTexture file="Interface\Buttons\UI-SquareButton-Up" desaturated="true">
      <Color r="0.75" g="0.75" b="0.75"/>
    </NormalTexture>
    <PushedTexture file="Interface\Buttons\UI-SquareButton-Down" desaturated="true">
      <Color r="0.75" g="0.75" b="0.75"/>
    </PushedTexture>
    <HighlightTexture file="Interface\Buttons\UI-Common-MouseHilight" alphaMode="ADD" alpha="0.75">
      <Anchors>
        <Anchor point="TOPLEFT" x="2" y="-2"/>
        <Anchor point="BOTTOMRIGHT" x="-2" y="2"/>
      </Anchors>
    </HighlightTexture>
  </Button>

  <Frame name="NysTDL_IconButtonPositionScripts" virtual="true">
    <!-- icon position adaptation scripts -->
    <Scripts>
      <OnMouseDown>
        <!-- nudge and dim the icon down a little -->
        local xOffset = -1;
        if (self.name == "UndoButton") then xOffset = -2; end

        local yOffset = -2;
        if (self.name == "UndoButton") then yOffset = -3; end
        if (self.name == "CategoryButton") then yOffset = -3; end

        self.Icon:SetPoint("CENTER", xOffset, yOffset) self.Icon:SetAlpha(0.5)
      </OnMouseDown>
      <OnMouseUp>
        <!-- reset the icon's position and opacity -->
        local xOffset = 0;
        if (self.name == "UndoButton") then xOffset = -0.5; end

        local yOffset = 0;
        if (self.name == "UndoButton") then yOffset = -0.5; end
        if (self.name == "CategoryButton") then yOffset = -1; end

        self.Icon:SetPoint("CENTER", xOffset, yOffset) self.Icon:SetAlpha(1)
      </OnMouseUp>
      <OnShow>
        <!-- reset the icon's position and opacity -->
        local xOffset = 0;
        if (self.name == "UndoButton") then xOffset = -0.5; end

        local yOffset = 0;
        if (self.name == "UndoButton") then yOffset = -0.5; end
        if (self.name == "CategoryButton") then yOffset = -1; end

        self.Icon:SetPoint("CENTER", xOffset, yOffset) self.Icon:SetAlpha(1)
      </OnShow>
    </Scripts>
  </Frame>

  <Frame name="NysTDL_IconButtonTooltipScripts" virtual="true">
    <Frames>
      <!-- small tooltip frame to describe use of the buttons -->
      <Frame parentKey="MiniTooltip" frameStrata="TOOLTIP" hidden="true">
        <Size x="0" y="26"/>
        <Backdrop bgFile="Interface\ChatFrame\ChatFrameBackground" edgeFile="Interface\Tooltips\UI-Tooltip-Border" tile="true">
          <TileSize val="16"/>
          <EdgeSize val="16"/>
          <BackgroundInsets>
            <AbsInset left="2" right="2" top="2" bottom="2"/>
          </BackgroundInsets>
          <Color r="0.05" g="0.05" b="0.05"/>
          <BorderColor r="0.5" g="0.5" b="0.5"/>
        </Backdrop>
        <Layers>
          <Layer level="ARTWORK">
            <FontString parentKey="Text" inherits="GameFontNormalSmall"/>
          </Layer>
        </Layers>
      </Frame>
    </Frames>

    <!-- Tooltip associated scripts -->
    <Scripts>
      <OnEnter>
        <!-- Show and reposition the tooltip -->
        self.MiniTooltip.Text:SetText(self.tooltip)
        self.MiniTooltip:SetWidth(self.MiniTooltip.Text:GetStringWidth()+16)
        local _, n = string.gsub(self.tooltip, "\n", "")
        if (n > 0) then
          self.MiniTooltip:SetHeight(26 + n*10)
        else
          self.MiniTooltip:SetHeight(26)
        end
        if (self.name == "AddButton") then
          self.MiniTooltip:SetPoint("BOTTOMRIGHT", self, "TOPLEFT", -3, 7)
        elseif (self.name == "TooltipResizeButton") then
          self.MiniTooltip:SetPoint("BOTTOMRIGHT", self, "BOTTOMLEFT", -5, 0)
        else
          self.MiniTooltip:SetPoint("RIGHT", self, "LEFT", 0, 0)
        end
        self.MiniTooltip:Show()
      </OnEnter>
      <OnLeave>
        <!-- Hide the tooltip -->
        self.MiniTooltip:Hide()
      </OnLeave>
    </Scripts>
  </Frame>

  <!-- Category button -->
  <Button name="NysTDL_CategoryButton" inherits="NysTDL_IconButtonTemplate, NysTDL_IconButtonTooltipScripts, NysTDL_IconButtonPositionScripts" virtual="true">
    <Size x="32" y="32"/>
    <KeyValues>
      <KeyValue key="tooltip" value="locale"/>
      <KeyValue key="name" value="CategoryButton"/>
    </KeyValues>
    <Layers>
      <Layer level="OVERLAY">
        <FontString parentKey="Icon" font="Fonts\FRIZQT__.TTF" inherits="GameFontNormalLarge" text="+">
          <FontHeight val="22"/>
          <Anchors>
            <Anchor point="CENTER"/>
          </Anchors>
        </FontString>
      </Layer>
    </Layers>
  </Button>

  <!-- Undo button -->
  <Button name="NysTDL_UndoButton" inherits="NysTDL_IconButtonTemplate, NysTDL_IconButtonTooltipScripts, NysTDL_IconButtonPositionScripts" virtual="true">
    <Size x="32" y="32"/>
    <KeyValues>
      <KeyValue key="tooltip" value="locale"/>
      <KeyValue key="name" value="UndoButton"/>
    </KeyValues>
    <Layers>
      <Layer level="OVERLAY">
        <Texture parentKey="Icon" file="Interface\Buttons\UI-RefreshButton">
          <Size x="14" y="14"/>
          <Anchors>
            <Anchor point="CENTER"/>
          </Anchors>
        </Texture>
      </Layer>
    </Layers>
  </Button>

  <!-- Tab Actions button -->
  <Button name="NysTDL_TabActionsButton" inherits="NysTDL_IconButtonTemplate, NysTDL_IconButtonTooltipScripts, NysTDL_IconButtonPositionScripts" virtual="true">
    <Size x="32" y="32"/>
    <KeyValues>
      <KeyValue key="tooltip" value="locale"/>
      <KeyValue key="name" value="TabActionsButton"/>
    </KeyValues>
    <Layers>
      <Layer level="OVERLAY">
        <Texture parentKey="Icon" file="Interface\BUTTONS\UI-GuildButton-MOTD-Up">
          <Size x="14" y="14"/>
          <Anchors>
            <Anchor point="CENTER"/>
          </Anchors>
        </Texture>
      </Layer>
    </Layers>
  </Button>

  <!-- Frame Options button -->
  <Button name="NysTDL_FrameOptionsButton" inherits="NysTDL_IconButtonTemplate, NysTDL_IconButtonTooltipScripts, NysTDL_IconButtonPositionScripts" virtual="true">
    <Size x="32" y="32"/>
    <KeyValues>
      <KeyValue key="tooltip" value="locale"/>
      <KeyValue key="name" value="FrameOptionsButton"/>
    </KeyValues>
    <Layers>
      <Layer level="OVERLAY">
        <Texture parentKey="Icon" file="Interface\BUTTONS\UI-GuildButton-OfficerNote-Up">
          <Size x="15" y="15"/>
          <Anchors>
            <Anchor point="CENTER"/>
          </Anchors>
        </Texture>
      </Layer>
    </Layers>
  </Button>

  <!-- Help button -->
  <Button name="NysTDL_HelpButton" inherits="InlineHyperlinkFrameTemplate, NysTDL_IconButtonTooltipScripts, NysTDL_IconButtonPositionScripts" virtual="true">
    <Size x="30" y="30"/>
    <KeyValues>
      <KeyValue key="tooltip" value="locale"/>
      <KeyValue key="name" value="HelpButton"/>
    </KeyValues>
    <Layers>
      <Layer level="OVERLAY">
        <Texture parentKey="Icon" file="Interface\COMMON\help-i">
          <Size x="40" y="40"/>
          <Anchors>
            <Anchor point="CENTER"/>
          </Anchors>
        </Texture>
      </Layer>
    </Layers>
  </Button>

  <!-- Close button -->
  <Button name="NysTDL_CloseButton" inherits="NysTDL_IconButtonTemplate, NysTDL_IconButtonPositionScripts" virtual="true">
    <Size x="25" y="25"/>
    <KeyValues>
      <KeyValue key="name" value="CloseButton"/>
    </KeyValues>
    <Layers>
      <Layer level="OVERLAY">
        <Texture parentKey="Icon" file="Interface\Buttons\UI-StopButton">
          <Size x="14" y="14"/>
          <Anchors>
            <Anchor point="CENTER"/>
          </Anchors>
        </Texture>
      </Layer>
    </Layers>
  </Button>

  <!-- Remove button -->
  <Button name="NysTDL_RemoveButton" inherits="InlineHyperlinkFrameTemplate, NysTDL_IconButtonPositionScripts" virtual="true">
    <Size x="13" y="13"/>
    <KeyValues>
      <KeyValue key="name" value="RemoveButton"/>
    </KeyValues>
    <Layers>
      <Layer level="OVERLAY">
        <Texture parentKey="Icon" file="Interface\Buttons\UI-StopButton">
          <Size x="14" y="14"/>
          <Anchors>
            <Anchor point="CENTER"/>
          </Anchors>
        </Texture>
      </Layer>
    </Layers>
  </Button>

  <!-- Favorite button -->
  <Button name="NysTDL_FavoriteButton" inherits="InlineHyperlinkFrameTemplate, NysTDL_IconButtonPositionScripts" virtual="true">
    <Size x="16" y="16"/> <!-- Size of interactable zone -->
    <KeyValues>
      <KeyValue key="name" value="FavoriteButton"/>
    </KeyValues>
    <Layers>
      <Layer level="BACKGROUND">
        <Texture parentKey="Icon" file="Interface\COMMON\FavoritesIcon">
          <Size x="26" y="26"/> <!-- Size of the texture -->
          <Anchors>
            <Anchor point="CENTER"/>
          </Anchors>
        </Texture>
      </Layer>
    </Layers>
  </Button>

  <!-- Description button -->
  <Button name="NysTDL_DescButton" inherits="InlineHyperlinkFrameTemplate, NysTDL_IconButtonPositionScripts" virtual="true">
    <Size x="13" y="13"/> <!-- Size of interactable zone -->
    <KeyValues>
      <KeyValue key="name" value="DescButton"/>
    </KeyValues>
    <Layers>
      <Layer level="OVERLAY">
        <Texture parentKey="Icon" file="Interface\BUTTONS\UI-GuildButton-PublicNote-Up">
          <Size x="13" y="13"/> <!-- Size of the texture -->
          <Anchors>
            <Anchor point="CENTER"/>
          </Anchors>
        </Texture>
      </Layer>
    </Layers>
  </Button>

  <!-- Add button -->
  <Button name="NysTDL_AddButton" inherits="NysTDL_IconButtonTooltipScripts, InlineHyperlinkFrameTemplate, NysTDL_IconButtonPositionScripts" virtual="true">
    <Size x="12" y="12"/>
    <KeyValues>
      <KeyValue key="tooltip" value="locale"/>
      <KeyValue key="name" value="AddButton"/>
    </KeyValues>
    <Layers>
      <Layer>
        <FontString parentKey="Icon" font="Fonts\FRIZQT__.TTF" inherits="GameFontNormalLarge" text="+">
          <FontHeight val="22"/>
          <Anchors>
            <Anchor point="CENTER"/>
          </Anchors>
        </FontString>
      </Layer>
    </Layers>
  </Button>

  <!-- resize button -->
  <Button name="NysTDL_ResizeButton" virtual="true">
    <Size x="16" y="16"/> <!-- Size of interactable zone -->
    <NormalTexture file="Interface\ChatFrame\UI-ChatIM-SizeGrabber-Up"/>
    <PushedTexture file="Interface\ChatFrame\UI-ChatIM-SizeGrabber-Down"/>
    <HighlightTexture file="Interface\ChatFrame\UI-ChatIM-SizeGrabber-Highlight" alphaMode="ADD"/>
  </Button>

  <!-- resize button with tooltip -->
  <Button name="NysTDL_TooltipResizeButton" inherits="NysTDL_IconButtonTooltipScripts" virtual="true">
    <Size x="16" y="16"/> <!-- Size of interactable zone -->
    <KeyValues>
      <KeyValue key="tooltip" value="locale"/>
      <KeyValue key="name" value="TooltipResizeButton"/>
    </KeyValues>
    <NormalTexture file="Interface\ChatFrame\UI-ChatIM-SizeGrabber-Up"/>
    <PushedTexture file="Interface\ChatFrame\UI-ChatIM-SizeGrabber-Down"/>
    <HighlightTexture file="Interface\ChatFrame\UI-ChatIM-SizeGrabber-Highlight" alphaMode="ADD"/>
  </Button>

  <!-- Normal button with nice highlight -->
  <Button name="NysTDL_NormalButton" virtual="true">
    <Size>
      <AbsDimension x="96" y="33"/>
  	</Size>
		<Layers>
			<Layer level="BACKGROUND">
				<Texture name="$parentLeft" file="Interface\Buttons\UI-SilverButtonLG-Left-Up">
					<Size>
						<AbsDimension x="32" y="46"/>
					</Size>
					<Anchors>
						<Anchor point="TOPLEFT" x="0" y="0"/>
					</Anchors>
				</Texture>
				<Texture name="$parentRight" file="Interface\Buttons\UI-SilverButtonLG-Right-Up">
					<Size>
						<AbsDimension x="32" y="46"/>
					</Size>
					<Anchors>
						<Anchor point="TOPRIGHT" x="0" y="0"/>
					</Anchors>
				</Texture>
				<Texture name="$parentMiddle" file="Interface\Buttons\UI-SilverButtonLG-Mid-Up">
					<Size>
						<AbsDimension x="32" y="46"/>
					</Size>
					<Anchors>
						<Anchor point="TOPLEFT" relativeTo="$parentLeft" relativePoint="TOPRIGHT" x="0" y="0"/>
						<Anchor point="TOPRIGHT" relativeTo="$parentRight" relativePoint="TOPLEFT" x="0" y="0"/>
					</Anchors>
				</Texture>
			</Layer>
			<Layer level="HIGHLIGHT">
				<Texture name="$parentLeft" file="Interface\Buttons\UI-SilverButtonLG-Left-Hi">
					<Size>
						<AbsDimension x="32" y="46"/>
					</Size>
					<Anchors>
						<Anchor point="TOPLEFT" x="0" y="0"/>
					</Anchors>
				</Texture>
				<Texture name="$parentRight" file="Interface\Buttons\UI-SilverButtonLG-Right-Hi">
					<Size>
						<AbsDimension x="32" y="46"/>
					</Size>
					<Anchors>
						<Anchor point="TOPRIGHT" x="0" y="0"/>
					</Anchors>
				</Texture>
				<Texture name="$parentMiddle" file="Interface\Buttons\UI-SilverButtonLG-Mid-Hi">
					<Size>
						<AbsDimension x="32" y="46"/>
					</Size>
					<Anchors>
						<Anchor point="TOPLEFT" relativeTo="$parentLeft" relativePoint="TOPRIGHT" x="0" y="0"/>
						<Anchor point="TOPRIGHT" relativeTo="$parentRight" relativePoint="TOPLEFT" x="0" y="0"/>
					</Anchors>
				</Texture>
			</Layer>
    </Layers>
		<Scripts>
			<OnMouseDown>
				if ( self:IsEnabled() ) then
					local name = self:GetName();
					_G[name.."Left"]:SetTexture("Interface\\Buttons\\UI-SilverButtonLG-Left-Down");
					_G[name.."Middle"]:SetTexture("Interface\\Buttons\\UI-SilverButtonLG-Mid-Down");
					_G[name.."Right"]:SetTexture("Interface\\Buttons\\UI-SilverButtonLG-Right-Down");
					local contentsFrame = _G[name.."ContentsFrame"];
					if ( contentsFrame ) then
						contentsFrame:SetPoint("TOPLEFT", -2, -1);
					end
				end
			</OnMouseDown>
			<OnMouseUp>
				if ( self:IsEnabled() ) then
					local name = self:GetName();
					_G[name.."Left"]:SetTexture("Interface\\Buttons\\UI-SilverButtonLG-Left-Up");
					_G[name.."Middle"]:SetTexture("Interface\\Buttons\\UI-SilverButtonLG-Mid-Up");
					_G[name.."Right"]:SetTexture("Interface\\Buttons\\UI-SilverButtonLG-Right-Up");
					local contentsFrame = _G[name.."ContentsFrame"];
					if ( contentsFrame ) then
						contentsFrame:SetPoint("TOPLEFT", 0, 0);
					end
				end
			</OnMouseUp>
		</Scripts>
	</Button>

</Ui>
